zotero2md/__init__.py
zotero2md/output_to_md.py
zotero2md/sample_params.json
zotero2md/test/__init__.py
zotero2md/test/test_utils.py
zotero2md/utils.py
zotero2md/zotero.py
zotero2md/zt2md.py
zotero2md-0.2.0.dist-info/WHEEL
zotero2md-0.2.0.dist-info/METADATA
zotero2md-0.2.0.dist-info/RECORD
